wiliot_deployment_tools/__init__.py
wiliot_deployment_tools/requirements.txt
wiliot_deployment_tools/version.py
wiliot_deployment_tools/ag/__init__.py
wiliot_deployment_tools/ag/ut_defines.py
wiliot_deployment_tools/ag/wlt_types.py
wiliot_deployment_tools/ag/wlt_types_ag.py
wiliot_deployment_tools/ag/wlt_types_data.py
wiliot_deployment_tools/ag/wlt_types_imports.py
wiliot_deployment_tools/api/__init__.py
wiliot_deployment_tools/api/extended_api.py
wiliot_deployment_tools/api/gw_ssid.py
wiliot_deployment_tools/api/s3_client.py
wiliot_deployment_tools/common/__init__.py
wiliot_deployment_tools/common/analysis_data_bricks.py
wiliot_deployment_tools/common/debug.py
wiliot_deployment_tools/common/utils.py
wiliot_deployment_tools/common/utils_defines.py
wiliot_deployment_tools/common/wltPb.proto
wiliot_deployment_tools/common/wltPb_pb2.py
wiliot_deployment_tools/common/wltPb_pb2.pyi
wiliot_deployment_tools/connectivity_analyzer/__init__.py
wiliot_deployment_tools/connectivity_analyzer/connectivity_analyzer.py
wiliot_deployment_tools/gw_certificate/__init__.py
wiliot_deployment_tools/gw_certificate/gw_certificate.py
wiliot_deployment_tools/gw_certificate/gw_certificate_cli.py
wiliot_deployment_tools/gw_certificate/api_if/__init__.py
wiliot_deployment_tools/gw_certificate/api_if/api_validation.py
wiliot_deployment_tools/gw_certificate/api_if/gw_capabilities.py
wiliot_deployment_tools/gw_certificate/api_if/200/data.json
wiliot_deployment_tools/gw_certificate/api_if/200/logs.json
wiliot_deployment_tools/gw_certificate/api_if/200/status.json
wiliot_deployment_tools/gw_certificate/api_if/201/data.json
wiliot_deployment_tools/gw_certificate/api_if/201/logs.json
wiliot_deployment_tools/gw_certificate/api_if/201/status.json
wiliot_deployment_tools/gw_certificate/api_if/202/data.json
wiliot_deployment_tools/gw_certificate/api_if/202/logs.json
wiliot_deployment_tools/gw_certificate/api_if/202/status.json
wiliot_deployment_tools/gw_certificate/api_if/203/data.json
wiliot_deployment_tools-4.1.54.dist-info/LICENSE
wiliot_deployment_tools-4.1.54.dist-info/METADATA
wiliot_deployment_tools-4.1.54.dist-info/WHEEL
wiliot_deployment_tools-4.1.54.dist-info/entry_points.txt
wiliot_deployment_tools-4.1.54.dist-info/top_level.txt
wiliot_deployment_tools-4.1.54.dist-info/RECORD
