Metadata-Version: 2.2
Name: wiliot-deployment-tools
Version: 4.1.54
Summary: A library for interacting with Wiliot's Deployment Tools
Home-page: 
Author: Wiliot
Author-email: support@wiliot.com
License: MIT
Project-URL: Bug Tracker, https://WILIOT-ZENDESK-URL
Classifier: Programming Language :: Python :: 3
Classifier: License :: OSI Approved :: MIT License
Classifier: Operating System :: OS Independent
Requires-Python: >=3.8
License-File: LICENSE
Requires-Dist: wiliot-core>=4.0.9
Requires-Dist: wiliot-api>=4.4.0
Requires-Dist: setuptools_scm>=7.1.0
Requires-Dist: bitstruct==8.17.0
Requires-Dist: bokeh==2.4.1
Requires-Dist: boto3==1.26.77
Requires-Dist: colorama==0.4.6
Requires-Dist: jsonpickle==3.0.1
Requires-Dist: numpy>=1.21.5
Requires-Dist: pandas==1.4.2
Requires-Dist: plotly==5.17.0
Requires-Dist: pytz==2022.7.1
Requires-Dist: requests>=2.28.1
Requires-Dist: setuptools>=65.6.3
Requires-Dist: shapely>=2.0.4
Requires-Dist: tabulate==0.8.10
Requires-Dist: backports.zoneinfo==0.2.1; python_version < "3.9.0"
Requires-Dist: tinytuya>=1.10.2
Requires-Dist: pyserial>=3.5
Requires-Dist: GitPython>=3.1.31
Requires-Dist: tzdata>=2023.3
Requires-Dist: confluent-kafka>=2.1.1
Requires-Dist: paho-mqtt==2.0.0
Requires-Dist: packaging>=23.1
Requires-Dist: scipy>=1.11.1
Requires-Dist: mplcursors>=0.5.2
Requires-Dist: matplotlib==3.8.4
Requires-Dist: pydantic
Requires-Dist: jinja2>=3.1.2
Requires-Dist: jsonschema>=4.19.0
Requires-Dist: statsmodels>=0.14.1
Requires-Dist: pycryptodome==3.14.1
Requires-Dist: protobuf==5.28.2
Dynamic: author
Dynamic: author-email
Dynamic: classifier
Dynamic: description
Dynamic: description-content-type
Dynamic: license
Dynamic: project-url
Dynamic: requires-dist
Dynamic: requires-python
Dynamic: summary
